[
  {
    "flavor": "Blue Razz Ice",
    "store": 1,
    "home": 0,
    "expiryDate": "09-27-2026",
    "category": "North Vision 15K"
  },
  {
    "flavor": "BlueBerry Watermelon",
    "store": 0,
    "home": 0,
    "expiryDate": "09-27-2026",
    "category": "North Vision 15K"
  },
  {
    "flavor": "Cherry Cola",
    "store": 1,
    "home": 0,
    "expiryDate": "09-27-2026",
    "category": "North Vision 15K"
  },
  {
    "flavor": "Cyan Berries",
    "store": 0,
    "home": 0,
    "expiryDate": "09-02-2026",
    "category": "North Vision 15K"
  },
  {
    "flavor": "Grape Twist",
    "store": 0,
    "home": 0,
    "expiryDate": "09-06-2026",
    "category": "North Vision 15K"
  },
  {
    "flavor": "Gummy Mint",
    "store": 0,
    "home": 0,
    "expiryDate": "09-02-2026",
    "category": "North Vision 15K"
  },
  {
    "flavor": "Juicy Peach",
    "store": 0,
    "home": 0,
    "expiryDate": "09-02-2026",
    "category": "North Vision 15K"
  },
  {
    "flavor": "Love Story",
    "store": 1,
    "home": 0,
    "expiryDate": "09-07-2026",
    "category": "North Vision 15K"
  },
  {
    "flavor": "Mexican Mango",
    "store": 0,
    "home": 0,
    "expiryDate": "08-24-2026",
    "category": "North Vision 15K"
  },
  {
    "flavor": "Miami Mint",
    "store": 1,
    "home": 0,
    "expiryDate": "08-16-2026",
    "category": "North Vision 15K"
  },
  {
    "flavor": "Mighty Mint",
    "store": 1,
    "home": 0,
    "expiryDate": "09-27-2026",
    "category": "North Vision 15K"
  },
  {
    "flavor": "Peach Pineapple Refresher",
    "store": 1,
    "home": 0,
    "expiryDate": "09-02-2026",
    "category": "North Vision 15K"
  },
  {
    "flavor": "Strawberry Dreamshake",
    "store": 0,
    "home": 0,
    "expiryDate": "09-02-2026",
    "category": "North Vision 15K"
  },
  {
    "flavor": "Strawberry Mango",
    "store": 1,
    "home": 0,
    "expiryDate": "08-16-2026",
    "category": "North Vision 15K"
  },
  {
    "flavor": "Strawnana Swirl",
    "store": 0,
    "home": 0,
    "expiryDate": "09-15-2026",
    "category": "North Vision 15K"
  },
  {
    "flavor": "Tropical Rainbow Blast",
    "store": 0,
    "home": 0,
    "expiryDate": "09-02-2026",
    "category": "North Vision 15K"
  },
  {
    "flavor": "Vanilla Tobacco",
    "store": 1,
    "home": 0,
    "expiryDate": "02-25-2027",
    "category": "North Vision 15K"
  }
]
